{
	"id": "a8fea7c6-a48d-4926-b6dc-4067bd453fe2",
	"name": "spotledev",
	"values": [
		{
			"key": "userid",
			"value": "3",
			"enabled": true
		},
		{
			"key": "postid",
			"value": "33",
			"enabled": true
		},
		{
			"key": "token",
			"value": "",
			"enabled": true
		},
		{
			"key": "title",
			"value": "demo title 33",
			"enabled": true
		},
		{
			"key": "bodytext",
			"value": "demo text 33",
			"enabled": true
		}
	],
	"_postman_variable_scope": "environment",
	"_postman_exported_at": "2020-08-23T03:23:34.978Z",
	"_postman_exported_using": "Postman/7.25.1"
}